tno/sdg/tabular/gen/cluster_based/__init__.py
tno/sdg/tabular/gen/cluster_based/generator.py
tno/sdg/tabular/gen/cluster_based/histogram.py
tno/sdg/tabular/gen/cluster_based/py.typed
tno/sdg/tabular/gen/cluster_based/util.py
tno/sdg/tabular/gen/cluster_based/test/__init__.py
tno/sdg/tabular/gen/cluster_based/test/conftest.py
tno/sdg/tabular/gen/cluster_based/test/test_categorical_histogram.py
tno/sdg/tabular/gen/cluster_based/test/test_continuous_histogram.py
tno/sdg/tabular/gen/cluster_based/test/test_generator.py
tno/sdg/tabular/gen/cluster_based/test/data/adult.data
tno.sdg.tabular.gen.cluster_based-0.2.0.dist-info/LICENSE
tno.sdg.tabular.gen.cluster_based-0.2.0.dist-info/METADATA
tno.sdg.tabular.gen.cluster_based-0.2.0.dist-info/WHEEL
tno.sdg.tabular.gen.cluster_based-0.2.0.dist-info/top_level.txt
tno.sdg.tabular.gen.cluster_based-0.2.0.dist-info/RECORD
