Metadata-Version: 2.1
Name: tno.sdg.tabular.gen.cluster_based
Version: 0.2.0
Summary: Cluster Based Synthetic Data Generation
Author-email: TNO PET Lab <petlab@tno.nl>
Maintainer-email: TNO PET Lab <petlab@tno.nl>
License: Apache License, Version 2.0
Project-URL: Homepage, https://pet.tno.nl/
Project-URL: Documentation, https://docs.pet.tno.nl/sdg/tabular/gen/cluster_based/0.2.0
Project-URL: Source, https://github.com/TNO-SDG/tabular.gen.cluster_based
Keywords: TNO,SDG,synthetic data,synthetic data generation,tabular
Platform: any
Classifier: License :: OSI Approved :: Apache Software License
Classifier: Programming Language :: Python :: 3
Classifier: Operating System :: OS Independent
Classifier: Intended Audience :: Developers
Classifier: Intended Audience :: Information Technology
Classifier: Intended Audience :: Science/Research
Classifier: Typing :: Typed
Classifier: Topic :: Scientific/Engineering
Requires-Python: >=3.9
License-File: LICENSE
Requires-Dist: pandas<3.0,>2.0
Requires-Dist: scikit-learn<2.0,>=1.0
Requires-Dist: typing_extensions>=4.4; python_version < "3.12"
Provides-Extra: tests
Requires-Dist: pytest>=8.1; extra == "tests"
Requires-Dist: matplotlib<4.0,>=3.0; extra == "tests"
Requires-Dist: pandas-stubs<3.0,>2.0; extra == "tests"
